hetzner_server_scouter/__init__.py
hetzner_server_scouter/__main__.py
hetzner_server_scouter/settings.py
hetzner_server_scouter/utils.py
hetzner_server_scouter/version.py
hetzner_server_scouter/db/__init__.py
hetzner_server_scouter/db/crud.py
hetzner_server_scouter/db/db_conf.py
hetzner_server_scouter/db/db_utils.py
hetzner_server_scouter/db/models.py
hetzner_server_scouter/notifications/crud.py
hetzner_server_scouter/notifications/models.py
hetzner_server_scouter/notifications/notify_telegram.py
hetzner_server_scouter-0.1.0.dist-info/LICENSE
hetzner_server_scouter-0.1.0.dist-info/METADATA
hetzner_server_scouter-0.1.0.dist-info/WHEEL
hetzner_server_scouter-0.1.0.dist-info/entry_points.txt
hetzner_server_scouter-0.1.0.dist-info/top_level.txt
hetzner_server_scouter-0.1.0.dist-info/RECORD
